{"errors":[],"warnings":[],"namedChunkGroups":{"polyfill":{"chunks":[3,0,7],"assets":["webpack-runtime-e7e14e7fb392cb988991.js","webpack-runtime-e7e14e7fb392cb988991.js.map","commons-ef6a0061850f6530d130.js","commons-ef6a0061850f6530d130.js.map","polyfill-977557a9e6d958500f0e.js","polyfill-977557a9e6d958500f0e.js.map"],"children":{},"childAssets":{}},"app":{"chunks":[3,8,6,0,4],"assets":["webpack-runtime-e7e14e7fb392cb988991.js","webpack-runtime-e7e14e7fb392cb988991.js.map","styles.19c77abfa9c3f596b986.css","styles-8fab2804fb6f85b824b6.js","styles-8fab2804fb6f85b824b6.js.map","framework-d585a04b7d285a7760d6.js","framework-d585a04b7d285a7760d6.js.map","commons-ef6a0061850f6530d130.js","commons-ef6a0061850f6530d130.js.map","app-9033dc546bfa3457cb3e.js","app-9033dc546bfa3457cb3e.js.map"],"children":{},"childAssets":{}},"component---src-pages-home-tsx":{"chunks":[2,1,0],"assets":["ea88be26-9a90f6bf0532c8ebd17b.js","ea88be26-9a90f6bf0532c8ebd17b.js.map","05d954cf-96fceb54e7803c7a2539.js","05d954cf-96fceb54e7803c7a2539.js.map","commons-ef6a0061850f6530d130.js","commons-ef6a0061850f6530d130.js.map"],"children":{},"childAssets":{}},"component---src-pages-index-tsx":{"chunks":[2,1,0,5],"assets":["ea88be26-9a90f6bf0532c8ebd17b.js","ea88be26-9a90f6bf0532c8ebd17b.js.map","05d954cf-96fceb54e7803c7a2539.js","05d954cf-96fceb54e7803c7a2539.js.map","commons-ef6a0061850f6530d130.js","commons-ef6a0061850f6530d130.js.map","component---src-pages-index-tsx-0f0572cc50d1ebe09002.js","component---src-pages-index-tsx-0f0572cc50d1ebe09002.js.map"],"children":{},"childAssets":{}}},"assetsByChunkName":{"polyfill":["webpack-runtime-e7e14e7fb392cb988991.js","commons-ef6a0061850f6530d130.js","polyfill-977557a9e6d958500f0e.js"],"app":["webpack-runtime-e7e14e7fb392cb988991.js","styles.19c77abfa9c3f596b986.css","styles-8fab2804fb6f85b824b6.js","framework-d585a04b7d285a7760d6.js","commons-ef6a0061850f6530d130.js","app-9033dc546bfa3457cb3e.js"],"component---src-pages-home-tsx":["ea88be26-9a90f6bf0532c8ebd17b.js","05d954cf-96fceb54e7803c7a2539.js","commons-ef6a0061850f6530d130.js"],"component---src-pages-index-tsx":["ea88be26-9a90f6bf0532c8ebd17b.js","05d954cf-96fceb54e7803c7a2539.js","commons-ef6a0061850f6530d130.js","component---src-pages-index-tsx-0f0572cc50d1ebe09002.js"]}}